ethers-0.1.1.dist-info/METADATA
ethers-0.1.1.dist-info/WHEEL
ethers-0.1.1.dist-info/license_files/LICENSE
ethers/__init__.py
ethers/ethers.cpython-39-darwin.so
ethers-0.1.1.dist-info/RECORD
