Metadata-Version: 2.1
Name: ethers
Version: 0.1.1
License-File: LICENSE
